README.md
setup.py
mpi4pyscf/__init__.py
mpi4pyscf.egg-info/PKG-INFO
mpi4pyscf.egg-info/SOURCES.txt
mpi4pyscf.egg-info/dependency_links.txt
mpi4pyscf.egg-info/requires.txt
mpi4pyscf.egg-info/top_level.txt
mpi4pyscf/cc/__init__.py
mpi4pyscf/cc/ccsd.py
mpi4pyscf/cc/ccsd_t.py
mpi4pyscf/dft/__init__.py
mpi4pyscf/dft/rks.py
mpi4pyscf/dft/uks.py
mpi4pyscf/lib/__init__.py
mpi4pyscf/lib/diis.py
mpi4pyscf/lib/logger.py
mpi4pyscf/mp/__init__.py
mpi4pyscf/mp/mp2.py
mpi4pyscf/pbc/__init__.py
mpi4pyscf/pbc/df/__init__.py
mpi4pyscf/pbc/df/aft.py
mpi4pyscf/pbc/df/aft_ao2mo.py
mpi4pyscf/pbc/df/aft_jk.py
mpi4pyscf/pbc/df/df.py
mpi4pyscf/pbc/df/df_ao2mo.py
mpi4pyscf/pbc/df/df_jk.py
mpi4pyscf/pbc/df/fft.py
mpi4pyscf/pbc/df/fft_jk.py
mpi4pyscf/pbc/df/mdf.py
mpi4pyscf/pbc/df/mdf_ao2mo.py
mpi4pyscf/pbc/df/mdf_jk.py
mpi4pyscf/pbc/gto/__init__.py
mpi4pyscf/pbc/gto/ecp.py
mpi4pyscf/scf/__init__.py
mpi4pyscf/scf/hf.py
mpi4pyscf/scf/uhf.py
mpi4pyscf/tools/__init__.py
mpi4pyscf/tools/mpi.py
mpi4pyscf/tools/mpi_pool.py